[{
  "Title": "solar panel water-cleaning",
  "topic": {
      "Guid": "5f4f043a-12c5-4f3d-8f5e-1eb3a78b43cf",
      "TopicType": "Structural",
      "TopicStatus": "in progress",
      "ReferenceLink": "https://api.replic-a.net/bcf/291",
      "Title": "solar panel water-cleaning",
      "Priority": "urgent",
      "Index": 291,
      "CreationAuthor": "User",
      "ModifiedAuthor": "User",
      "DueDate": "2024-09-15T14:12:52",
      "Description": "solar panel is dirty.Request fo cleaner",
      "Type": "DEMANDE / REQUEST",
      "Status": "Open",
      "Budget": 90000,
      "Progress": "usd"
    }
},
{"Title": "solar panel damage",
  "topic": {
      "Guid": "5f4f043a-12c5-4f3d-8f5e-1eb3a78b43cf",
      "TopicType": "Issue",
      "TopicStatus": "Active",
      "ReferenceLink": "https://api.replic-a.net/bcf/291",
      "Title": "solar panel damage",
      "Priority": "urgent",
      "Index": 291,
      "CreationAuthor": "User",
      "ModifiedAuthor": "User",
      "DueDate": "2024-09-15T14:12:52",
      "Description": "solar panel is damaged,it should be repaired",
      "Type": "DEMANDE / REQUEST",
      "Status": "Active",
      "Budget": 0,
      "Progress": 0
    }},
    {"Title": "Co2 monitoring",
  "topic": {
      "Guid": "5f4f043a-12c5-4f3d-8f5e-1eb3a78b43cf",
      "TopicType": "Issue",
      "TopicStatus": "Active",
      "ReferenceLink": "https://api.replic-a.net/bcf/291",
      "Title": "Co2 monitoring",
      "Priority": "urgent",
      "Index": 291,
      "CreationAuthor": "User",
      "ModifiedAuthor": "User",
      "DueDate": "2024-09-15T14:12:52",
      "Description": "co2 level is greater than 800ppm(  data  )",
      "Type": "DEMANDE / REQUEST",
      "Status": "Active",
      "Budget": 0,
      "Progress": 0}},
      {"Title": "HVAC systems",
  "topic": {
      "Guid": "5f4f043a-12c5-4f3d-8f5e-1eb3a78b43cf",
      "TopicType": "Request",
      "TopicStatus": "in progress",
      "ReferenceLink": "https://api.replic-a.net/bcf/291",
      "Title": "HVAC systems",
      "Priority": "urgent",
      "Index": 291,
      "CreationAuthor": "User",
      "ModifiedAuthor": "User",
      "DueDate": "2024-09-15T14:12:52",
      "Description": "HVAC systems should be turned on",
      "Type": "DEMANDE / REQUEST",
      "Status": "In progress",
      "Budget": 0,
      "Progress": 0}},{"Title": "Temperature level monitoring",
  "topic": {
      "Guid": "5f4f043a-12c5-4f3d-8f5e-1eb3a78b43cf",
      "TopicType": "Issue",
      "TopicStatus": "Active",
      "ReferenceLink": "https://api.replic-a.net/bcf/291",
      "Title": "Temperature level monitoring",
      "Priority": "High",
      "Index": 291,
      "CreationAuthor": "User",
      "ModifiedAuthor": "User",
      "DueDate": "2024-09-15T14:12:52",
      "Description": "tempertaure level is low/high(depends on data)",
      "Type": "Issue",
      "Status": "In progress",
      "Budget": 0,
      "Progress": 0}},{"Title": "Air conditioning system",
      "topic": {
          "Guid": "5f4f043a-12c5-4f3d-8f5e-1eb3a78b43cf",
          "TopicType": "Request",
          "TopicStatus": "in progress",
          "ReferenceLink": "https://api.replic-a.net/bcf/291",
          "Title": "Air conditioning system",
          "Priority": "High",
          "Index": 291,
          "CreationAuthor": "User",
          "ModifiedAuthor": "User",
          "DueDate": "2024-09-15T14:12:52",
          "Description": "air conditioning system should increase/decrease the temperature",
          "Type": "DEMANDE / REQUEST",
          "Status": "In progress",
          "Budget": 0,
          "Progress": 0}}
]
  